python_bebop/__init__.py
python_bebop/bebop.py
python_bebop-1.3.2.dist-info/LICENSE
python_bebop-1.3.2.dist-info/METADATA
python_bebop-1.3.2.dist-info/WHEEL
python_bebop-1.3.2.dist-info/top_level.txt
python_bebop-1.3.2.dist-info/RECORD
