Metadata-Version: 2.1
Name: python-bebop
Version: 1.3.2
Summary: bebop runtime bindings for Python
Home-page: https://github.com/liquidiert/bebop
Author: Korbinian Habereder
Author-email: korbinian.habereder@gmail.com
Project-URL: Bug Tracker, https://github.com/liquidiert/bebop
Classifier: Programming Language :: Python :: 3
Classifier: License :: OSI Approved :: Apache Software License
Classifier: Operating System :: OS Independent
Requires-Python: >=3.8
License-File: LICENSE
